{"id":1123505,"translations":[{"iso_3166_1":"US","iso_639_1":"en","name":"English","english_name":"English","data":{"biography":"Kim Jung-nan (born Kim Hyun-ah on July 16, 1971) is a South Korean actress. Kim made her acting debut in 1991, but received a new surge of popularity after starring in A Gentleman's Dignity in 2012.","name":"Kim Jung-nan","primary":false}},{"iso_3166_1":"KR","iso_639_1":"ko","name":"한국어/조선말","english_name":"Korean","data":{"biography":"","name":"김정난","primary":true}},{"iso_3166_1":"CN","iso_639_1":"zh","name":"普通话","english_name":"Mandarin","data":{"biography":"金正兰，原名金贤雅，1971年7月16日出生于韩国，韩国女演员，毕业于东国大学演剧电影科。","name":"金贞兰","primary":false}},{"iso_3166_1":"UA","iso_639_1":"uk","name":"Український","english_name":"Ukrainian","data":{"biography":"","name":"Кім Джон Нан","primary":false}},{"iso_3166_1":"TW","iso_639_1":"zh","name":"普通话","english_name":"Mandarin","data":{"biography":"","name":"金正蘭","primary":false}},{"iso_3166_1":"FR","iso_639_1":"fr","name":"Français","english_name":"French","data":{"biography":"Kim Jung-nan est une actrice sud-coréenne. Kim a fait ses débuts d'actrice en 1991, mais a connu un regain de popularité après avoir joué dans A Gentleman's Dignity en 2012. Wikipédia","name":"Kim Jeong-nan","primary":false}},{"iso_3166_1":"HK","iso_639_1":"zh","name":"普通话","english_name":"Mandarin","data":{"biography":"金貞蘭，原名金賢雅，1971 年 7 月 16 日出生於韓國，韓國女演員，畢業於東國大學演劇電影科。","name":"金貞蘭","primary":false}},{"iso_3166_1":"RU","iso_639_1":"ru","name":"Pусский","english_name":"Russian","data":{"biography":"","name":"Ким Чжон Нан","primary":false}}]}