{"id":1222060,"translations":[{"iso_3166_1":"US","iso_639_1":"en","name":"English","english_name":"English","data":{"biography":"Kenyu Horiuchi is a Japanese voice actor. In 2002 he founded his own voice acting management office, Kenyu Office.","name":"Kenyu Horiuchi","primary":false}},{"iso_3166_1":"BR","iso_639_1":"pt","name":"Português","english_name":"Portuguese","data":{"biography":"","name":"Kenyu Horiuchi","primary":false}},{"iso_3166_1":"JP","iso_639_1":"ja","name":"日本語","english_name":"Japanese","data":{"biography":"","name":"堀内賢雄","primary":true}},{"iso_3166_1":"CN","iso_639_1":"zh","name":"普通话","english_name":"Mandarin","data":{"biography":"","name":"堀内贤雄","primary":false}},{"iso_3166_1":"DE","iso_639_1":"de","name":"Deutsch","english_name":"German","data":{"biography":"","name":"Kenyu Horiuchi","primary":false}},{"iso_3166_1":"ES","iso_639_1":"es","name":"Español","english_name":"Spanish","data":{"biography":"Kenyu Horiuchi es un actor de doblaje japonés. En 2002 fundó su propia agencia de representación de actores de doblaje, Kenyu Office.","name":"Kenyu Horiuchi","primary":false}},{"iso_3166_1":"FR","iso_639_1":"fr","name":"Français","english_name":"French","data":{"biography":"","name":"Kenyu Horiuchi","primary":false}},{"iso_3166_1":"KR","iso_639_1":"ko","name":"한국어/조선말","english_name":"Korean","data":{"biography":"","name":"호리우치 켄유","primary":false}},{"iso_3166_1":"RU","iso_639_1":"ru","name":"Pусский","english_name":"Russian","data":{"biography":"","name":"Кэнъю Хориути","primary":false}},{"iso_3166_1":"CZ","iso_639_1":"cs","name":"Český","english_name":"Czech","data":{"biography":"","name":"Ken’jú Horiuči","primary":false}},{"iso_3166_1":"IT","iso_639_1":"it","name":"Italiano","english_name":"Italian","data":{"biography":"","name":"Ken'yū Horiuchi","primary":false}},{"iso_3166_1":"PT","iso_639_1":"pt","name":"Português","english_name":"Portuguese","data":{"biography":"","name":"Ken'yū Horiuchi","primary":false}},{"iso_3166_1":"TH","iso_639_1":"th","name":"ภาษาไทย","english_name":"Thai","data":{"biography":"","name":"โฮริอุจิ เคนยู","primary":false}},{"iso_3166_1":"TW","iso_639_1":"zh","name":"普通话","english_name":"Mandarin","data":{"biography":"堀內賢雄是日本的男性聲優、旁白。出身於靜岡縣御殿場市，所屬公司為 Kenyu Office，同時也是該事務所的創辦人。","name":"堀內賢雄","primary":false}},{"iso_3166_1":"UA","iso_639_1":"uk","name":"Український","english_name":"Ukrainian","data":{"biography":"","name":"Кен'ю Хоріучі","primary":false}},{"iso_3166_1":"HK","iso_639_1":"zh","name":"普通话","english_name":"Mandarin","data":{"biography":"堀內賢雄是日本的男性聲優、旁白。出身於靜岡縣禦殿場市，所屬公司為 Kenyu Office，同時也是該事務所的創辦人。","name":"堀內賢雄","primary":false}},{"iso_3166_1":"MX","iso_639_1":"es","name":"Español","english_name":"Spanish","data":{"biography":"Kenyū Horiuchi es un actor de doblaje japonés. En 2002 fundó su propia agencia de representación de actores de doblaje, Kenyu Office.","name":"Kenyū Horiuchi","primary":false}}]}