{"id":2027747,"translations":[{"iso_3166_1":"CN","iso_639_1":"zh","name":"普通话","english_name":"Mandarin","data":{"biography":"　　1988年，在电视剧《大学》中出任男主角，获得飞天奖最佳男主角提名。2001年，凭借电影《一曲柔情》获“中国电影家学会奖”最佳演员奖提名。2003年，主演胡玫执导电视剧《汉武大帝》，饰演卫青。2006年，主演《玫瑰绽放的年代》饰演邱云飞一角。2010年，参演谍战剧《黎明之前》饰演“水手”段海平。","name":"陆剑民","primary":false}},{"iso_3166_1":"US","iso_639_1":"en","name":"English","english_name":"English","data":{"biography":"","name":"Lu Jianmin","primary":false}},{"iso_3166_1":"TW","iso_639_1":"zh","name":"普通话","english_name":"Mandarin","data":{"biography":"","name":"Lu Jianmin","primary":true}},{"iso_3166_1":"HK","iso_639_1":"zh","name":"普通话","english_name":"Mandarin","data":{"biography":"1988 年，在電視劇《大學》中出任男主角，獲得飛天獎最佳男主角提名。2001 年，憑藉電影《一曲柔情》獲“中國電影家學會獎”最佳演員獎提名。2003 年，主演胡玫執導電視劇《漢武大帝》，飾演衞青。2006 年，主演《玫瑰綻放的年代》飾演邱雲飛一角。2010 年，參演諜戰劇《黎明之前》飾演“水手”段海平。","name":"陸劍民","primary":false}}]}