{"adult":false,"backdrop_path":"/w4HqCpNojW3kbgtj4qHCnf5G7bf.jpg","created_by":[{"id":1233035,"credit_id":"635b0939fd630000819728b8","name":"Ben Watkins","original_name":"Ben Watkins","gender":2,"profile_path":"/6YDvWYMZFoPVu0IIXxEDiVaaOZe.jpg"}],"episode_run_time":[],"first_air_date":"2024-11-14","genres":[{"id":80,"name":"Phim Hình Sự"},{"id":18,"name":"Phim Chính Kịch"},{"id":9648,"name":"Phim Bí Ẩn"}],"homepage":"https://www.amazon.com/dp/B0D6HFBLMP","id":213306,"in_production":true,"languages":["en"],"last_air_date":"2026-02-25","last_episode_to_air":{"id":6588611,"name":"Episode 5","overview":"","vote_average":3.8,"vote_count":3,"air_date":"2026-02-25","episode_number":5,"episode_type":"standard","production_code":"","runtime":57,"season_number":2,"show_id":213306,"still_path":"/yWlLpHk71gboUWEAfMPHNOAx7qu.jpg"},"name":"Cross: Lằn Ranh Công Lý","next_episode_to_air":{"id":6588612,"name":"Episode 6","overview":"","vote_average":0,"vote_count":0,"air_date":"2026-03-04","episode_number":6,"episode_type":"standard","production_code":"","runtime":null,"season_number":2,"show_id":213306,"still_path":null},"networks":[{"id":1024,"logo_path":"/w7HfLNm9CWwRmAMU58udl2L7We7.png","name":"Prime Video","origin_country":""}],"number_of_episodes":16,"number_of_seasons":2,"origin_country":["US"],"original_language":"en","original_name":"Cross","overview":"","popularity":26.4809,"poster_path":"/6hhKdavCEZi8d584ZtIrQIrBvZI.jpg","production_companies":[{"id":87731,"logo_path":"/8PeKdSO13vYTod2HAJsV2m7mRr0.png","name":"Skydance Television","origin_country":"US"},{"id":210099,"logo_path":"/g5oRCNCi8kNVb8gEoSoIcqkhjmR.png","name":"Amazon MGM Studios","origin_country":"US"},{"id":228633,"logo_path":"/of4mmVt6egYaO9oERJbuUxMOTkj.png","name":"Paramount Television Studios","origin_country":"US"},{"id":244791,"logo_path":"/6LpW4cbrWpegqKML8NmVNEAGCv.png","name":"Blue Monday Productions","origin_country":"US"},{"id":270146,"logo_path":"/4r6rIxegOrrVeJwqRxpzNrCRQMD.png","name":"Paramount Television Studios","origin_country":"US"}],"production_countries":[{"iso_3166_1":"US","name":"United States of America"}],"seasons":[{"air_date":"2024-11-14","episode_count":8,"id":314334,"name":"Season 1","overview":"","poster_path":"/iMFlZFr8HxTyEnjT7mtFI2qYI3H.jpg","season_number":1,"vote_average":4.4},{"air_date":"2026-02-11","episode_count":8,"id":479152,"name":"Season 2","overview":"","poster_path":"/6hhKdavCEZi8d584ZtIrQIrBvZI.jpg","season_number":2,"vote_average":3.1}],"spoken_languages":[{"english_name":"English","iso_639_1":"en","name":"English"}],"status":"Returning Series","tagline":"","type":"Scripted","vote_average":7,"vote_count":252}